README.md
setup.py
sservice/__init__.py
sservice.egg-info/PKG-INFO
sservice.egg-info/SOURCES.txt
sservice.egg-info/dependency_links.txt
sservice.egg-info/requires.txt
sservice.egg-info/top_level.txt